QuatNet/__init__.py
QuatNet/quaternion_layers.py
QuatNet/quaternion_ops.py
tests/__init__.py
QuatNet-0.1.2.dist-info/LICENSE
QuatNet-0.1.2.dist-info/METADATA
QuatNet-0.1.2.dist-info/WHEEL
QuatNet-0.1.2.dist-info/top_level.txt
QuatNet-0.1.2.dist-info/RECORD
