Metadata-Version: 2.1
Name: QuatNet
Version: 0.1.2
Summary: A PyTorch-based library for quaternion neural networks
Home-page: https://github.com/DataSenseiAryan/QuatNet
Author: aryan chaudhary
Author-email: datasenseiaryan@gmail.com
Classifier: Programming Language :: Python :: 3
Classifier: License :: OSI Approved :: MIT License
Classifier: Operating System :: OS Independent
Requires-Python: ==3.8.19
License-File: LICENSE
Requires-Dist: torch ==2.3.0
Requires-Dist: numpy ==1.24.4
Requires-Dist: scipy ==1.10.1
